olympuswifi/__init__.py
olympuswifi/camera.py
olympuswifi/download.py
olympuswifi/errors.py
olympuswifi/liveview.py
olympuswifi/log2gpx.py
olympuswifi/main.py
olympuswifi-0.9.3.dist-info/METADATA
olympuswifi-0.9.3.dist-info/WHEEL
olympuswifi-0.9.3.dist-info/entry_points.txt
olympuswifi-0.9.3.dist-info/licenses/LICENSE
olympuswifi-0.9.3.dist-info/RECORD
