Metadata-Version: 2.4
Name: olympuswifi
Version: 0.9.3
Summary: Connect to wifi-enabled Olympus camera, show liveview, set the clock, take pictures, download images, change settings, turn it off.
Project-URL: Documentation, https://olympus-wifi.readthedocs.org
Project-URL: Homepage, https://github.com/joergmlpts/olympus-wifi
Project-URL: Bug Tracker, https://github.com/joergmlpts/olympus-wifi/issues
Author-email: joergmlpts <joergmlpts@outlook.com>
License-File: LICENSE
Keywords: camera,liveview,olympus,wifi
Classifier: Development Status :: 5 - Production/Stable
Classifier: Intended Audience :: Developers
Classifier: Intended Audience :: End Users/Desktop
Classifier: License :: OSI Approved :: MIT License
Classifier: Operating System :: POSIX
Classifier: Programming Language :: Python
Classifier: Programming Language :: Python :: 3
Classifier: Programming Language :: Python :: 3 :: Only
Classifier: Programming Language :: Python :: 3.7
Classifier: Programming Language :: Python :: 3.8
Classifier: Programming Language :: Python :: 3.9
Classifier: Programming Language :: Python :: 3.10
Classifier: Programming Language :: Python :: 3.11
Classifier: Programming Language :: Python :: 3.12
Classifier: Programming Language :: Python :: 3.13
Requires-Python: >=3.7
Requires-Dist: pillow
Requires-Dist: requests
